macApp/__init__.py
macApp/macOS.py
macApp/utils.py
macApp-1.1.dist-info/LICENSE
macApp-1.1.dist-info/METADATA
macApp-1.1.dist-info/WHEEL
macApp-1.1.dist-info/top_level.txt
macApp-1.1.dist-info/RECORD
